vcloud/__init__.py
vcloud/api/__init__.py
vcloud/api/rest/__init__.py
vcloud/api/rest/schema/__init__.py
vcloud/api/rest/schema/ovf/__init__.py
vcloud/api/rest/schema/ovf/annotation_section_type.py
vcloud/api/rest/schema/ovf/automatic_recovery_action.py
vcloud/api/rest/schema/ovf/automatic_shutdown_action.py
vcloud/api/rest/schema/ovf/automatic_startup_action.py
vcloud/api/rest/schema/ovf/cim_any_simple_type.py
vcloud/api/rest/schema/ovf/cim_base64_binary.py
vcloud/api/rest/schema/ovf/cim_boolean.py
vcloud/api/rest/schema/ovf/cim_byte.py
vcloud/api/rest/schema/ovf/cim_char16.py
vcloud/api/rest/schema/ovf/cim_date_time.py
vcloud/api/rest/schema/ovf/cim_double.py
vcloud/api/rest/schema/ovf/cim_float.py
vcloud/api/rest/schema/ovf/cim_hex_binary.py
vcloud/api/rest/schema/ovf/cim_int.py
vcloud/api/rest/schema/ovf/cim_long.py
vcloud/api/rest/schema/ovf/cim_reference.py
vcloud/api/rest/schema/ovf/cim_resource_allocation_setting_data_type.py
vcloud/api/rest/schema/ovf/cim_short.py
vcloud/api/rest/schema/ovf/cim_string.py
vcloud/api/rest/schema/ovf/cim_unsigned_byte.py
vcloud/api/rest/schema/ovf/cim_unsigned_int.py
vcloud/api/rest/schema/ovf/cim_unsigned_long.py
vcloud/api/rest/schema/ovf/cim_unsigned_short.py
vcloud/api/rest/schema/ovf/cim_virtual_system_setting_data_type.py
vcloud/api/rest/schema/ovf/configuration.py
vcloud/api/rest/schema/ovf/consumer_visibility.py
vcloud/api/rest/schema/ovf/content_type.py
vcloud/api/rest/schema/ovf/deployment_option_section_configuration.py
vcloud/api/rest/schema/ovf/deployment_option_section_type.py
vcloud/api/rest/schema/ovf/disk_section_type.py
vcloud/api/rest/schema/ovf/envelope_type.py
vcloud/api/rest/schema/ovf/eula_section_type.py
vcloud/api/rest/schema/ovf/file_type.py
vcloud/api/rest/schema/ovf/icon.py
vcloud/api/rest/schema/ovf/install_section_type.py
vcloud/api/rest/schema/ovf/item.py
vcloud/api/rest/schema/ovf/mapping_behavior.py
vcloud/api/rest/schema/ovf/msg.py
vcloud/api/rest/schema/ovf/msg_type.py
vcd_api_schemas_type-10.3.0.dev35.dist-info/AUTHORS
vcd_api_schemas_type-10.3.0.dev35.dist-info/LICENSE
vcd_api_schemas_type-10.3.0.dev35.dist-info/METADATA
vcd_api_schemas_type-10.3.0.dev35.dist-info/WHEEL
vcd_api_schemas_type-10.3.0.dev35.dist-info/pbr.json
vcd_api_schemas_type-10.3.0.dev35.dist-info/top_level.txt
vcd_api_schemas_type-10.3.0.dev35.dist-info/RECORD
