Metadata-Version: 2.1
Name: vcd-api-schemas-type
Version: 10.3.0.dev35
Summary: VMware vCloud Director Python API Schemas Type
Home-page: https://github.com/vmware/vcd-api-schemas
Author: Rajesh Kumar
Author-email: rajeshk@vmware.com
License: BSD-2
Platform: UNKNOWN
Classifier: Environment :: Console
Classifier: Intended Audience :: System Administrators
Classifier: Intended Audience :: Developers
Classifier: Operating System :: POSIX :: Linux
Classifier: Operating System :: MacOS :: MacOS X
Classifier: Operating System :: Microsoft :: Windows
Classifier: Programming Language :: Python
Classifier: Programming Language :: Python :: 3
Requires-Python: >=3
License-File: LICENSE
License-File: AUTHORS
